volumetricspy/__init__.py
volumetricspy/montecarlo.py
volumetricspy/stats/__init__.py
volumetricspy/stats/grid.py
volumetricspy/stats/krigging.py
volumetricspy/stats/points.py
volumetricspy/stats/sgs.py
volumetricspy/stats/transforms.py
volumetricspy/stats/variograms.py
volumetricspy/utils/__init__.py
volumetricspy/utils/formulas.py
volumetricspy/volumetrics.py
volumetricspy-0.1.10.dist-info/LICENSE
volumetricspy-0.1.10.dist-info/WHEEL
volumetricspy-0.1.10.dist-info/METADATA
volumetricspy-0.1.10.dist-info/RECORD
