Metadata-Version: 2.1
Name: volumetricspy
Version: 0.1.10
Summary: Oil & Gas Tool for estimating Original in Place Resources
License: MIT
Author: Santiago Cuervo
Author-email: scuervo91@gmail.com
Requires-Python: >=3.8,<3.11
Classifier: License :: OSI Approved :: MIT License
Classifier: Programming Language :: Python :: 3
Classifier: Programming Language :: Python :: 3.8
Classifier: Programming Language :: Python :: 3.9
Classifier: Programming Language :: Python :: 3.10
Requires-Dist: Shapely (>=1.7.1,<2.0.0)
Requires-Dist: folium (==0.13.0)
Requires-Dist: geopandas (>=0.10.2,<0.11.0)
Requires-Dist: mapclassify (>=2.4.3,<3.0.0)
Requires-Dist: matplotlib (>=3.4.3,<4.0.0)
Requires-Dist: numpy (>=1.21.2,<2.0.0)
Requires-Dist: pandas (>=1.3.2,<2.0.0)
Requires-Dist: plotly (>=5.10.0,<6.0.0)
Requires-Dist: pydantic (>=1.8.2,<2.0.0)
Requires-Dist: pyvista (>=0.31.3,<0.32.0)
Requires-Dist: scikit-image (>=0.18.2,<0.19.0)
Requires-Dist: scipy (>=1.7.1,<2.0.0)
Requires-Dist: seaborn (>=0.11.2,<0.12.0)
Requires-Dist: zmapio (>=0.6.0,<0.7.0)
